ZConfig/__init__.py
ZConfig/_schema_utils.py
ZConfig/cfgparser.py
ZConfig/cmdline.py
ZConfig/datatypes.py
ZConfig/info.py
ZConfig/loader.py
ZConfig/matcher.py
ZConfig/pygments.py
ZConfig/schema.py
ZConfig/schema2html.py
ZConfig/schemaless.py
ZConfig/schemaless.txt
ZConfig/sphinx.py
ZConfig/substitution.py
ZConfig/url.py
ZConfig/validator.py
ZConfig/components/__init__.py
ZConfig/components/basic/__init__.py
ZConfig/components/basic/component.xml
ZConfig/components/basic/mapping.py
ZConfig/components/basic/mapping.xml
ZConfig/components/basic/tests/__init__.py
ZConfig/components/basic/tests/test_mapping.py
ZConfig/components/logger/__init__.py
ZConfig/components/logger/abstract.xml
ZConfig/components/logger/base-logger.xml
ZConfig/components/logger/component.xml
ZConfig/components/logger/datatypes.py
ZConfig/components/logger/eventlog.xml
ZConfig/components/logger/factory.py
ZConfig/components/logger/formatter.py
ZConfig/components/logger/handlers.py
ZConfig/components/logger/handlers.xml
ZConfig/components/logger/logger.py
ZConfig/components/logger/logger.xml
ZConfig/components/logger/loghandler.py
ZConfig/components/logger/tests/__init__.py
ZConfig/components/logger/tests/support.py
ZConfig/components/logger/tests/test_formatter.py
ZConfig/components/logger/tests/test_logger.py
ZConfig/tests/__init__.py
ZConfig/tests/bad-component.xml
ZConfig/tests/bad-component2.xml
ZConfig/tests/foosample.zip
ZConfig/tests/sphinx_test_schema.xml
ZConfig/tests/support.py
ZConfig/tests/test_cfgimports.py
ZConfig/tests/test_cmdline.py
ZConfig/tests/test_config.py
ZConfig/tests/test_cookbook.py
ZConfig/tests/test_datatypes.py
ZConfig/tests/test_info.py
ZConfig/tests/test_loader.py
ZConfig/tests/test_matcher.py
ZConfig/tests/test_pygments.py
ZConfig/tests/test_readme.py
ZConfig/tests/test_schema.py
ZConfig/tests/test_schema2html.py
ZConfig/tests/test_schemaless.py
ZConfig/tests/test_subst.py
ZConfig/tests/test_validator.py
ZConfig/tests/input/base-datatype1.xml
ZConfig-4.1.dist-info/LICENSE.txt
ZConfig-4.1.dist-info/METADATA
ZConfig-4.1.dist-info/WHEEL
ZConfig-4.1.dist-info/entry_points.txt
ZConfig-4.1.dist-info/top_level.txt
ZConfig-4.1.dist-info/RECORD
