Metadata-Version: 2.1
Name: ZConfig
Version: 4.1
Summary: Structured Configuration Library
Home-page: https://github.com/zopefoundation/ZConfig/
Author: Fred L. Drake, Jr.
Author-email: fred@fdrake.net
Maintainer: Zope Foundation and Contributors
License: ZPL 2.1
Keywords: configuration structured simple flexible typed hierarchy logging
Classifier: Development Status :: 5 - Production/Stable
Classifier: Intended Audience :: Developers
Classifier: Intended Audience :: System Administrators
Classifier: License :: OSI Approved :: Zope Public License
Classifier: Operating System :: OS Independent
Classifier: Programming Language :: Python
Classifier: Programming Language :: Python :: 3
Classifier: Programming Language :: Python :: 3.7
Classifier: Programming Language :: Python :: 3.8
Classifier: Programming Language :: Python :: 3.9
Classifier: Programming Language :: Python :: 3.10
Classifier: Programming Language :: Python :: 3.11
Classifier: Programming Language :: Python :: 3.12
Classifier: Programming Language :: Python :: Implementation :: CPython
Classifier: Programming Language :: Python :: Implementation :: PyPy
Classifier: Operating System :: OS Independent
Classifier: Topic :: Software Development
Requires-Python: >=3.7
License-File: LICENSE.txt
Provides-Extra: test
Requires-Dist: docutils; extra == "test"
Requires-Dist: manuel; extra == "test"
Requires-Dist: zope.exceptions; extra == "test"
Requires-Dist: zope.testrunner; extra == "test"
Provides-Extra: docs
Requires-Dist: sphinx-rtd-theme; extra == "docs"
Requires-Dist: sphinxcontrib-programoutput; extra == "docs"
